xodex/__init__.py
xodex/__main__.py
xodex/config.py
xodex/config_store.py
xodex/main.py
xodex/repl.py
xodex/setup.py
xodex/core/__init__.py
xodex/core/agent.py
xodex/core/context.py
xodex/core/tools.py
xodex/core/typing.py
xodex/prompts/__init__.py
xodex/prompts/system.py
xodex/prompts/xodex-cli.txt
xodex/providers/__init__.py
xodex/providers/deepseek_provider.py
xodex/providers/gemini_provider.py
xodex/providers/grok_provider.py
xodex/providers/openai_provider.py
xodex_cli-0.2.4.dist-info/METADATA
xodex_cli-0.2.4.dist-info/WHEEL
xodex_cli-0.2.4.dist-info/entry_points.txt
xodex_cli-0.2.4.dist-info/licenses/LICENSE
xodex_cli-0.2.4.dist-info/RECORD
