Metadata-Version: 2.4
Name: xodex-cli
Version: 0.2.4
Summary: CLI Agente de IA (DeepSeek | OpenAI | Gemini | Grok) para terminal, com contexto de projeto e ferramentas de dev.
Author: xodex-cli
License-File: LICENSE
Requires-Python: >=3.10
Requires-Dist: google-generativeai>=0.7.2
Requires-Dist: keyring>=25.0.0
Requires-Dist: openai>=1.51.2
Requires-Dist: platformdirs>=4.2.0
Requires-Dist: prompt-toolkit>=3.0.47
Requires-Dist: python-dotenv>=1.0.1
Requires-Dist: requests>=2.32.3
